MANIFEST.in
README.md
db_url.py
setup.py
db_url.egg-info/PKG-INFO
db_url.egg-info/SOURCES.txt
db_url.egg-info/dependency_links.txt
db_url.egg-info/entry_points.txt
db_url.egg-info/top_level.txt