Metadata-Version: 1.0
Name: db-url
Version: 0.2.2
Summary: UNKNOWN
Home-page: UNKNOWN
Author: UNKNOWN
Author-email: UNKNOWN
License: Public Domain
Platform: UNKNOWN
